IndovinaLaParola/IndovinaLaParola.py
IndovinaLaParola/__init__.py
IndovinaLaParola/main.py
tests/Integration_Test_IndovinaLaParola.py
tests/Unit_Test_IndovinaLaParola.py
tests/__init__.py
IndovinaLaParola-1.1.8.dist-info/METADATA
IndovinaLaParola-1.1.8.dist-info/WHEEL
IndovinaLaParola-1.1.8.dist-info/entry_points.txt
IndovinaLaParola-1.1.8.dist-info/top_level.txt
IndovinaLaParola-1.1.8.dist-info/RECORD
