Metadata-Version: 2.1
Name: IndovinaLaParola
Version: 1.1.8
Summary: Un gioco semplice di indovina la parola
Author: Gasa Industries
Requires-Python: >=3.6
Requires-Dist: setuptools
